cas_sdss_mcp/__init__.py
cas_sdss_mcp/_version.py
cas_sdss_mcp/app.py
cas_sdss_mcp/util.py
cas_sdss_mcp/data/database_names.parquet
cas_sdss_mcp/data/tbls_cols.parquet
cas_sdss_mcp/data/x_match_fns.parquet
cas_sdss_mcp-0.2.0.dist-info/licenses/LICENSE
cas_sdss_mcp-0.2.0.dist-info/METADATA
cas_sdss_mcp-0.2.0.dist-info/WHEEL
cas_sdss_mcp-0.2.0.dist-info/entry_points.txt
cas_sdss_mcp-0.2.0.dist-info/top_level.txt
cas_sdss_mcp-0.2.0.dist-info/RECORD
