Metadata-Version: 2.4
Name: cas_sdss_mcp
Version: 0.2.0
Summary: An MCP service for building queries against SDSS catalogs.
Author-email: JHU Data Science and AI Institute <ai@jhu.edu>
Project-URL: homepage, https://github.com/idies/cas-jobs-sdss-mcp
Project-URL: documentation, https://github.com/idies/cas-jobs-sdss-mcp
Project-URL: repository, https://github.com/idies/cas-jobs-sdss-mcp
Requires-Python: >=3.11
License-File: LICENSE
Requires-Dist: mcp[cli]>=1.3.0
Requires-Dist: pandas>=2.3.3
Requires-Dist: pip>=25.3
Requires-Dist: pyarrow>=22.0.0
Requires-Dist: requests>=2.32.5
Dynamic: license-file
